filext/__init__.py
filext/classifiers.py
filext/utils.py
tests/__init__.py
tests/conftest.py
tests/test_classifiers.py
tests/test_demo.py
tests/test_utils.py
filext-0.2.2.dist-info/LICENSE
filext-0.2.2.dist-info/METADATA
filext-0.2.2.dist-info/WHEEL
filext-0.2.2.dist-info/top_level.txt
filext-0.2.2.dist-info/RECORD
